traintrack/__init__.py
traintrack/command_line_pipe.py
traintrack/run_pipeline.py
traintrack/utils/__init__.py
traintrack/utils/config_utils.py
traintrack/utils/data_utils.py
traintrack/utils/model_utils.py
traintrack-0.1.6.dist-info/LICENSE.md
traintrack-0.1.6.dist-info/METADATA
traintrack-0.1.6.dist-info/WHEEL
traintrack-0.1.6.dist-info/entry_points.txt
traintrack-0.1.6.dist-info/top_level.txt
traintrack-0.1.6.dist-info/RECORD
