Metadata-Version: 2.1
Name: traintrack
Version: 0.1.6
Summary: A simple helper to run pipelines of PytorchLightning models
Home-page: https://github.com/murnanedaniel/train-track
Author: Daniel Murnane
License: Apache License, Version 2.0
Keywords: Machine Learning,MLOps,Pytorch,PytorchLightning,Lightning,Pipeline
License-File: LICENSE.md
Requires-Dist: numpy
Requires-Dist: scipy
Requires-Dist: pandas
Requires-Dist: matplotlib
Requires-Dist: scikit-learn
Requires-Dist: pyyaml >=5.1
Requires-Dist: pytorch-lightning
Requires-Dist: decorator
Requires-Dist: more-itertools
Requires-Dist: simple-slurm
Requires-Dist: memory-profiler
